.testr.conf
AUTHORS
CONTRIBUTING.rst
ChangeLog
HACKING.rst
MANIFEST.in
README.rst
babel.cfg
install_valence.sh
requirements.txt
setup.cfg
setup.py
test-requirements.txt
tox.ini
api-ref/source/conf.py
api-ref/source/index.rst
api-ref/source/parameters.yaml
api-ref/source/valence-api-v1-devices.inc
api-ref/source/valence-api-v1-flavors.inc
api-ref/source/valence-api-v1-nodes.inc
api-ref/source/valence-api-v1-pods.inc
api-ref/source/valence-api-v1-pooled.inc
api-ref/source/valence-api-v1-racks.inc
api-ref/source/valence-api-v1-system.inc
api-ref/source/valence-api-version.inc
api-ref/source/mockup/api-root-response.json
api-ref/source/mockup/api-v1-root-response.json
api-ref/source/mockup/composed-node-create-request.json
api-ref/source/mockup/composed-node-create-response.json
api-ref/source/mockup/composed-node-create-via-flavor-request.json
api-ref/source/mockup/composed-node-get-asset.json
api-ref/source/mockup/composed-node-get-response.json
api-ref/source/mockup/composed-nodes-list-response.json
api-ref/source/mockup/compute-system-get-response.json
api-ref/source/mockup/compute-system-inventory-get-response.json
api-ref/source/mockup/compute-systems-list-response.json
api-ref/source/mockup/devices-get-response.json
api-ref/source/mockup/devices-list-response.json
api-ref/source/mockup/devices-sync-response.json
api-ref/source/mockup/flavor-create-request.json
api-ref/source/mockup/flavor-create-response.json
api-ref/source/mockup/flavor-list-response.json
api-ref/source/mockup/node-post-action-attach-request.json
api-ref/source/mockup/node-reset-state-request.json
api-ref/source/mockup/node-set-boot-soruce-request.json
api-ref/source/mockup/node-update-name-info-request.json
api-ref/source/mockup/pod-manager-create-request.json
api-ref/source/mockup/pod-manager-create-response.json
api-ref/source/mockup/pod-manager-get-response.json
api-ref/source/mockup/pod-managers-list-response.json
api-ref/source/mockup/rack-get-response.json
valence.egg-info/PKG-INFO
valence.egg-info/SOURCES.txt
valence.egg-info/dependency_links.txt
valence.egg-info/entry_points.txt
valence.egg-info/not-zip-safe
valence.egg-info/pbr.json
valence.egg-info/requires.txt
valence.egg-info/top_level.txt
